{
    "raw_text": "SainiNaz\nfresher\nProfile\nBBA graduate - Fresher with less than 1 year experience is\nseeking a full time position in a reputable organization.\nCommitted\nto utilizing my skills to further the mission of a\nCompany.\nBringing fortha motivated attitude and avariety of powerful skills.\nAble to effectivelyself-manage during independent projects,as\nwell as collaborate as part of a productive team.\nEducation\nKendriya Vidyalaya No. 2 Salt Lake\nat Kolkata\nHigher Secondary(HS) Graduate.\nI cleared my 12the higher secondaryboard from Kendriya\nVidyalaya No.2SaltLake\nwith 71.2%\nSister Nivedita\nUniversity\nat Kolkata\nUnderGraduate\nIdid my BBA (digital\nmarketing) from Sister Nivedita University with cgpa of 7.28.\nInternships\nContent\nWriting at Team Everest NGO at Volunteer,\nKolkata\nSeptember 2023-Present\nI Did Internship As Story Content\nWriting for Team Everest NGO.\nDeveloped and managed a team of content writers to produce content\non\na\nconsistent basis\n\u2022 Managed a team of freelance writers to ensure\nall content was delivered on time\nand within budget\nAddress\nHC BlockSector - ii, Police Abasan\nSalt Lake\nKolkata,\nWest Bengal, 700106\nIndia\nEmail\nsaininaaz1435@gmail.com\nPhone\n9903904898\nDate / Place Of Birth\n28/12/2001, West Bengal\nDriving License\nNone\nNationality\nIndian\nSkills\nCommunication\nSkills\nConflict\nResolution\nLeadership Skills\nDecision Making\nProblem\nSolving\nAdaptability\nMicrosoftOffice Word\nMicrosoftPowerPoint\nTime Management\nMicrosoft\nExcel\nLeadership\nMicrosoft\nOffice\nAbility\nto Workin a Team\nHobbies\nDrawing, Sketching. Singing\nand\nPlayingGuitar.\nLanguages\nHindi\nEnglish\nBengali\n",
    "personal_info": {
        "name": "Saininaz",
        "email": "saininaaz1435@gmail.com",
        "phone": "9903904898",
        "linkedin": null,
        "github": null,
        "location": "Kolkata"
    },
    "resume_score": 90,
    "education_summary": "Post Graduate: No, Doctorate: No, Graduate (Bachelor's): Yes, UG (Diploma/ITI): No, HSC: Yes, SSC: Yes",
    "improvement_suggestions": [
        "Consider adding or pursuing Postgraduate (Master's, PGD) or Doctorate education.",
        "List certifications or training programs."
    ],
    "ai_skill_suggestions": [],
    "predicted_job_field": {
        "job_title": "No matching job found in knowledge base.",
        "skills": [
            "bba",
            "communication",
            "excel"
        ],
        "preferred_location": "Kolkata",
        "recommended_courses": []
    }
}