{
    "raw_text": "RUPESH JADHAV\n7387248170 ∥UmargamRoad, Gujarat\nrupeshjadhav200211@gmail.com ∥linkedin.com/RupeshJadhav∥github.com/RupeshJadhav\nSUMMARY\nFull Stack Developer with hands-on experience in building scalable web applications using the MERN stack and PHP.\nKnowledgeable in blockchain development, AI/ML, and IoT systems, with exposure to developing decentralized apps\n(dApps), smart contracts, and data-driven applications. Passionate about delivering secure, performant solutions\nacross the tech stack.\nEDUCATION\n• St. John College of Engineering and Management, Palghar, Maharashtra\nJune 2025\nBachelor of Technology in Artificial Intelligence and Machine Learning\nCGPA: 8.4\n• APMS College of Science, Commerce and Arts, Talasari, Maharashtra\nMarch 2021\nHSC - 79.83%\n• Madhyamik Vidyalaya, Talasari, Maharashtra\nMarch 2019\nSSC - 84.80%\nINTERNSHIPS\n• Udyog Suvidha Kendra\nDec 2024 – Present\nRole: Full Stack Developer (Blockchain + MERN + PHP)\n– Worked on a PHP and MERN based admin portal for form management and internal dashboard tools,\nhandling user data, transaction logs, and user queries.\n– Developed a Raydium-like decentralized platform on Solana using Rust and the Anchor framework, with\nReact and Solana-Web3.js for frontend integration and wallet support.\n• Rigel Infotech\nJune 2024 – July 2024\nRole: Full Stack Development Intern (MERN)\n– Completed hands-on training in full stack web development using the MERN stack (MongoDB, Express.js,\nReact.js, Node.js).\n– Developed dynamic web applications and RESTful APIs, focusing on component-based UI with React and\nbackend services with Node.js and Express. Integrated MongoDB for data storage and implemented CRUD\noperations to manage application data.\nSKILLS\n• Frontend: HTML, CSS, JavaScript, React.js, Tailwind CSS, Bootstrap, TypeScript, Redux\n• Backend: Node.js, Express.js, PHP, Laravel, RESTful APIs\n• Database: MongoDB, MySQL\n• Blockchain: Ethereum, Solana, Smart Contracts (Solidity, Rust), Web3.js, Ethers.js\n• AI/ML: Python, Scikit-learn, Pandas, NumPy, TensorFlow, Keras, PyTorch, Matplotlib, Seaborn, OpenCV,\nNLP, NLTK, spaCy, Hugging Face Transformers, LLMs (e.g., GPT, BERT), Deep Learning, Model Deployment\n(Flask/FastAPI)\n• IoT: Arduino, Embedded C, ESP32, SIM800L, Sensors Integration, Serial Communication, GSM-based Mes-\nsaging, Real-time Monitoring\n• IDEs & Tools: Git, GitHub, Postman, XAMPP, VS Code, Jupyter Notebook, Google Colab, Anaconda\n• Soft Skills: Problem Solving, Critical Thinking, Analytical Mindset, Communication Skills, Collaboration and\nTeamwork, Adaptability, Curiosity and Continuous Learning, Time Management, Open-Mindedness\nPROJECTS\n• AI Virtual Assistant (Rasa + NLP + Python)\nDeveloped a Windows-based AI assistant using Rasa for conversational AI and NLP pipelines. Enabled voice-\nactivated commands and intelligent task automation such as opening applications, searching the web, sending\nemails, and providing system updates. Integrated speech recognition, text-to-speech (TTS), and custom intent\nhandling for a seamless interactive user experience.\n• PsycheCounselAI – AI Mental Health Chatbot (MERN + LLM)\nDeveloped a mental health support web app using the MERN stack integrated with a large language model\n(LLM) to provide ChatGPT-like conversational therapy features. Designed to assist users with stress, anxiety,\nand emotional concerns through empathetic and intelligent dialogue. Implemented secure user authentication,\nsession tracking, and a responsive chat interface.\n• Blockchain-Based Face Recognition System (Python, OpenCV, Rust, IPFS)\nDeveloped a secure face recognition system integrated with blockchain for identity verification. Used OpenCV\nfor face detection and recognition, while storing encrypted facial data hashes on the Solana blockchain via smart\ncontracts.\nImplemented IPFS for decentralized image storage and ensured tamper-proof identity validation\nwith blockchain immutability. This system can be applied to secure access control, KYC, and digital identity\nmanagement.\n• IoT-Based Smart Energy Meter System (Arduino, Embedded C, SIM800L, Sensors)\nDeveloped a standalone energy monitoring and automated billing system using Arduino programmed in Embed-\nded C. Utilized current and voltage sensors to measure power consumption in real-time. Integrated SIM800L\nGSM module to send SMS alerts containing usage statistics and billing details directly to users. Enabled mobile-\nbased payment and remote recharge functionality via SIM-based communication. Designed for areas with limited\ninternet access, this system supports prepaid and postpaid billing models, providing an affordable, accessible\nsolution for smart energy management in rural and semi-urban regions.\nCERTIFICATIONS & COURSES\n• Full Stack Web Development Bootcamp\n• Data Analysis using Python\n• Solana Smart Contract Development with Anchor\n• 100 days of Machine Learning\n•\nFundamentals of Deep Learning\nACHIEVEMENTS\n• 2nd Place, MegaHack 2024 – Developed an IoT-based energy meter system with real-time analytics and\nautomated billing system.\n• 3rd Position, XZIBIT 2023 – IoT-based smart energy tracking and automated billing system.\nPOSITIONS OF RESPONSIBILITY\n• Core Member, ASCAI AIML Student Club, 2023-2024\n• Joint Technical Head, ISTE, 2023-2024\n• Lead Developer, E-Club, 2023-2024\nLANGUAGES\nEnglish , Hindi , Marathi\n",
    "personal_info": {
        "name": "Rupesh Jadhav",
        "email": "rupeshjadhav200211@gmail.com",
        "phone": "7387248170",
        "linkedin": "linkedin.com/in/RupeshJadhavgithub",
        "github": "github.com/RupeshJadhav",
        "location": "Gujarat"
    },
    "resume_score": 90,
    "education_summary": "Post Graduate: No, Doctorate: No, Graduate (Bachelor's): Yes, UG (Diploma/ITI): No, HSC: Yes, SSC: Yes",
    "improvement_suggestions": [
        "Consider adding or pursuing Postgraduate (Master's, PGD) or Doctorate education."
    ],
    "ai_skill_suggestions": [
        "tensorflow",
        "deep learning",
        "numpy",
        "classification",
        "regression",
        "seaborn",
        "streamlit",
        "python",
        "machine learning",
        "clustering",
        "data visualization",
        "pandas",
        "statistics",
        "scikit-learn",
        "matplotlib",
        "pytorch",
        "flask"
    ],
    "predicted_job_field": {
        "top_matches": [
            {
                "title": "Data Scientist",
                "confidence": 0.85,
                "confidence_percent": "85%"
            },
            {
                "title": "AI/ML Engineer",
                "confidence": 0.79,
                "confidence_percent": "79%"
            },
            {
                "title": "AI Engineer",
                "confidence": 0.79,
                "confidence_percent": "79%"
            }
        ],
        "job_title": "Data Scientist",
        "skills": [
            "100 Days Of Machine Learning",
            "A Php",
            "Access",
            "Adaptability",
            "Ai",
            "Anaconda",
            "Analytical Mindset",
            "Arduino",
            "Arduino Programmed In Embed-",
            "Bootstrap",
            "Collaboration And",
            "Commerce And Arts, Talasari, Maharashtra",
            "Communication Skills",
            "Continuous Learning",
            "Critical Thinking",
            "Css",
            "Curiosity",
            "Data Analysis Using Python",
            "Database: Mongodb, Mysql",
            "Deep Learning",
            "Embedded C",
            "Ethereum",
            "Ethers.js",
            "Express",
            "Flask",
            "Full Stack Web Development Bootcamp",
            "Git",
            "Google Colab",
            "Gsm-based Mes-",
            "Html",
            "Hugging Face Transformers",
            "Internal Dashboard Tools",
            "Javascript",
            "Jupyter",
            "Keras",
            "Laravel",
            "Llms E.g.",
            "Machine Learning",
            "Madhyamik Vidyalaya, Talasari, Maharashtra",
            "Matplotlib",
            "Model Deployment",
            "Mongodb",
            "Mongodb, Mysql",
            "Mysql",
            "Nlp",
            "Nlp Pipelines",
            "Node.Js",
            "Numpy",
            "On Component-based Ui With React",
            "Opencv",
            "Palghar, Maharashtra",
            "Pandas",
            "Php",
            "Postman",
            "Problem-Solving",
            "Python",
            "Pytorch",
            "Rasa For Conversational Ai",
            "React",
            "Real-time Monitoring",
            "Redux",
            "Restful Apis",
            "Rigel Infotech",
            "Rust",
            "Saging",
            "Scikit-Learn",
            "Seaborn",
            "Sensors Integration",
            "Serial Communication",
            "Smart Contracts Solidity",
            "Solana",
            "Spacy",
            "Tailwind Css",
            "Talasari, Maharashtra",
            "Teamwork",
            "Tensorflow",
            "The Anchor Framework",
            "The Mern Stack",
            "Time Management",
            "Typescript",
            "Udyog Suvidha Kendra",
            "Vs Code"
        ],
        "preferred_location": "Gujarat",
        "recommended_courses": {
            "Data Scientist": [
                "Machine Learning by Andrew Ng - https://www.coursera.org/learn/machine-learning",
                "R Programming for Data Analysis - https://www.datacamp.com/courses/free-introduction-to-r",
                "Data Science with Python - https://www.coursera.org/specializations/data-science-python"
            ],
            "AI/ML Engineer": [
                "Deep Learning Specialization - https://www.coursera.org/specializations/deep-learning"
            ],
            "AI Engineer": [
                "Machine Learning by Andrew Ng - https://www.coursera.org/learn/machine-learning",
                "Deep Learning Specialization - https://www.coursera.org/specializations/deep-learning",
                "AI For Everyone - https://www.coursera.org/learn/ai-for-everyone"
            ]
        }
    }
}