{
    "raw_text": "Mahima Kishor Jaiswal \nFresher \nAn independent and self motivated B.tech Engineering student willing to obtain a fresher position in a fast paced organization where my\ntechnical skills and creative thinking will be tested. I'm self motivated learner with a eagerness to learn new things. \nmahimajaiswal244@gmail.com \n9158944603 \nAurangabad, MH, India \nlinkedin.com/in/mahima-jaiswal-848728240 \nEDUCATION \nB.Tech in Electronics and Telecommunication\nEngineering \nDeogiri Institute of Engineering and\nManagement Studies, Aurangabad-431001 \n2020 - 2024,  \nCGPA - 8.05 \nDiploma in Electronics and\nTelecommunication Engineering \nMSS College of engineering and technology,\nJalna-431203 \n2020,  \n69.47% \nSSC \nYashwant Vidhyalay, Selu \n2013,  \n71.60% \nINTERNSHIPS \nSoftware Testing-Intern \nGTT(Global Talent Track)-Virtual mode \n04/2023 - 05/2023,  \nThe training session begins with an introduction to the fundamentals of\nsoftware testing, importance of testing in the software development and\nthe different types of testing, testing tools and frameworks. \nCore Java-Intern \nCSR initiative by Capgemini and FUEL \n02/2023 - 04/2023,  \nAurangabad \nAs a java intern at FUEL provides various aspects of java development,\nincluding OOPS, algorithm and software design pattern. Also get hands-\non projects and experience. \nATM System Project \nBus Reservation System Project \nCyber Security Virtual Internship \nForage \n08/2022 - 09/2022,  \nDuring the internship there is task module to complete. \nCO-CURRICULAR ACTIVITY \nElementry Workshop on MEP system Designing (2017) \nTechnophilia (2019) \nSKILLS \nHTML/CSS \nProject Management \nComputer Skills \nMS o\ufb03ce (Excel, PowerPoint, Word) \nMySQL \nACADEMIC PROJECTS \nLibrary Management System (2023) \nI developed the Library Management System using Java \nIndustrial Temperature Controller (2022) \nI developed a device that monitor and control the temperature of\nindustry \nBidirectional Visitors Counter (2019) \ni developed a device using 8051 Microcontroller is helpful to count\nthe number of people enterning or leaving a hall and displays it on an\nLCD \nCERTIFICATES \nFuture Skills Training in Core Java and Aptitude Training\n (2023) \nFUEL \nCompletion Certi\ufb01cate of Python (2023) \nIBM \nLearning Java (2023) \nLinkedIn Learning \nCloud Fundamental (2023) \nEXCELR \nPython and Django Framework (2021) \nUdemy \nACHIEVEMENTS \nParticipated in State Level Rangoli Competition (2021) \nLANGUAGES \nEnglish \nProfessional Working Pro\ufb01ciency \nHindi \nFull Professional Pro\ufb01ciency \nMarathi \nFull Professional Pro\ufb01ciency \nINTERESTS \nSketching \nRangoli \nMusic \nTasks \nTasks. \n",
    "personal_info": {
        "name": "Mahima Kishor Jaiswal",
        "email": "mahimajaiswal244@gmail.com",
        "phone": "9158944603",
        "linkedin": "linkedin.com/in/mahima-jaiswal-848728240",
        "github": null,
        "location": "Aurangabad"
    },
    "resume_score": 90,
    "education_summary": "Post Graduate: No, Doctorate: No, Graduate (Bachelor's): Yes, UG (Diploma/ITI): Yes, HSC: No, SSC: Yes",
    "improvement_suggestions": [
        "Consider adding or pursuing Postgraduate (Master's, PGD) or Doctorate education."
    ],
    "ai_skill_suggestions": [],
    "predicted_job_field": {
        "top_matches": [
            {
                "title": "Entry-Level / Undefined",
                "confidence": 0.0,
                "confidence_percent": "0%"
            }
        ],
        "job_title": "Entry-Level / Undefined",
        "skills": [
            "css",
            "software testing",
            "training",
            "microcontroller",
            "mysql",
            "html",
            "python",
            "tools",
            "java",
            "excel"
        ],
        "preferred_location": "Aurangabad",
        "recommended_courses": {
            "Entry-Level / Undefined": []
        }
    }
}