{
    "raw_text": " \nSAYALI DESHMUKH \nMaharashtra | 8550931823 | saydesh02@gmail.com | www.linkedin.com/in/sayali-deshmukh-399032283 \n \nSUMMARY* \nEnthusiastic and detail-focused Organic Chemist with a solid academic background and practical experience in \norganic synthesis and analytical techniques. Skilled in using tools like NMR, IR, and GC-MS to analyze and \ncharacterize compounds. Eager to bring creativity and precision to research and development in pharmaceuticals, \nmaterials, or chemical industries, contributing to meaningful innovations and reliable outcomes.  \n  \nPROFESSIONAL EXPERIENCE \n   \nKonkan Gyanpeeth Engineering College \n \n \n \n \n                                  Karjat - Raigad \nAssistant  Professor \n \n \n \n \n \n \n      \n      \n                      Jan 2024-Present  \n \nAs an enthusiastic Assistant Professor of Chemistry with 11 months of hands-on teaching experience, I take pride \nin creating engaging and relatable learning experiences for my students. I enjoy mentoring and guiding learners \nwhile designing curricula that bridge theoretical concepts with real-world applications. My goal is to inspire \ncuriosity, foster collaboration, and support student growth while contributing meaningfully to academic research \nand innovation. \n \nLEADERSHIP EXPERIENCE \n   \nBARC(Bhabha Atomic Research Center) \n \n \n \n         \n \n       Trombay -  Mumbai \nProject Trainee \n \n \n     \n \n        \n  \n        \n \n \n       Jan 2023-April 2023 \n \n \nI am a motivated individual with 3 months of practical experience in the Radiopharmaceuticals Department at \nBARC, where I had the opportunity to work on exciting projects. I gained hands-on experience in synthesizing \nradiopharmaceuticals, conducting experiments, and analyzing data with a focus on precision and safety. I'm \npassionate about advancing research in radiopharmaceuticals and contributing to their impactful applications in \nmedicine and diagnostics. \n \nEDUCATION \n \n                                                                                                                                  \nMUMBAI UNIVERSITY \n \n \n \n \n \n \n               \nPOST GRAUDATION IN ORGANIC CHEMISTRY                                                                       2023  \nWith 9.03 \n \nMUMBAI UNIVERSITY  \nBACHELOR OF SCIENCE                                                                                                                  2021 \nWith 7.83 \n \n \n \nLANGUAGES:   English \u2013 Fluently \n                           Hindi \u2013 Fluently  \n                           Marathi \u2013 Fluently \n \n \nINTERESTS:  Designing creative synthetic methods, NMR, IR, Chromatography, HPLC, Team Work, Purification, Time \nManagement, Tutoring, Arts, Volunteering, Collecting Data. \n \n \n \n \n \nConnect with us:  \nWebsite |  Facebook | Instagram | Tiktok | LinkedIn | Pinterest | Youtube \n \n \n \n \n \n",
    "personal_info": {
        "name": "Sayali Deshmukh",
        "email": "saydesh02@gmail.com",
        "phone": "8550931823",
        "linkedin": "linkedin.com/in/sayali-deshmukh-399032283",
        "github": null,
        "location": "Mumbai"
    },
    "resume_score": 75,
    "education_summary": "Post Graduate: Yes, Graduate (Bachelor's): Yes, UG (Diploma/ITI): No, HSC: No, SSC: No",
    "improvement_suggestions": [
        "Include Diploma/ITI or Higher Secondary (12th) education.",
        "Mention your Secondary School (10th) education.",
        "Mention any internships or trainee roles you've done.",
        "List certifications or training programs."
    ],
    "ai_skill_suggestions": [
        "switchboard",
        "wiring",
        "load calculation"
    ],
    "predicted_job_field": {
        "job_title": "Electrician",
        "skills": [
            "safety",
            "radiopharmaceuticals",
            "plc",
            "synthesis",
            "experiments",
            "gc-ms",
            "ir",
            "hplc",
            "cad",
            "research",
            "organic chemistry",
            "chromatography",
            "pharmaceutical",
            "mba",
            "icu",
            "tools",
            "nmr",
            "purification"
        ],
        "preferred_location": "Mumbai",
        "recommended_courses": [
            "Electrical Wiring - https://www.udemy.com/course/electrical-wiring",
            "Basic Electrical Engineering - https://www.coursera.org/learn/basic-electrical",
            "Solar Energy Basics - https://www.edx.org/course/solar-energy"
        ]
    }
}