{
    "raw_text": "YESH SHIVHARE \nMOBILE: +91 8823099701| EMAIL: yashshivhare353@gmail.com \nADDRESS: Guna, Madhya Pradesh \nLINKEDIN: https://www.linkedin.com/in/yesh-shivhare-896975226 \n \n \n \n \n \n \n  \nCAREER OBJECTIVE \n \nSeeking a career in a motivating environment where my skills and attitude enable me to help further growth and development of organization \n \n  \nINTERNSHIP \n \nEdelweiss Broking Limited, Indore (9th Aug \u2013 9th Sep 2019) \nEdelweiss Group is complete financial services & strongly presence in equity capital market, financing, assets management verticals. \nWork & Responsibility: \n\uf0fc \nResearch and generate list of potential customers\uf020\n\uf0fc \nAdvise clients in different assets classes like Debt, Equity, Mutual Funds, Structured Products, etc.\uf020\n\uf0fc \nHelp develop client relationships and retain existing accounts\uf020\n\uf0fc \nAssists in evaluating new sponsorship opportunities\uf020\n\uf0fc \nLearn and apply sales techniques\uf020\n\uf0fc \nMaintain sales records\uf020\nPROJECT\uf020\uf020\uf020\uf020\n\uf020PROJECT (MARKET RESEARCH ON CUSTOMER SHARE FOR NUTRITION FOODS)\uf020\n\uf0fc \nStudied and collected data on customer share on nutrition food and analyzed the responses of 50 customer \n\uf0fc \nPrepared a report on the conclusion derived from data analysis. \n \n \nEDUCATIONAL INFORMATION \nXth, S.t Mary\u2019s high school \nMP Bord, Guna, Madhya Pradesh, 2015 \nPercentage \u2013 60% \nXIIth, Delhi Public School \n CBSE, Guna, Madhya Pradesh, 2017 \nPercentage \u2013 55% \nBachelors of Commerce (computer) \nGandhi Vocational College \nJIWAJI University, Guna, Madhya Pradesh, 2020 \nPercentage \u2013 61% \nMaster In business Administration  \nIndore Indira Business School, \nRenaissance University, Indore, Madhya Pradesh (Pursuing) \nPERSONAL DETAILS \nDate of Birth: 24th May, 1999 \nMarital Status: Single \nNationality: Indian \nLanguages Known: English, Hindi \nFather\u2019s Name: Mr. Dileep shivhare \nMother\u2019s Name: Mrs. Neetu Shivhare \nIT SKILLS \n \n\uf0fc \nMicrosoft Office \n(Excel, Word & PowerPoint) \n \n \nPERSONALITY TRAITS \n \n\uf0fc \nTeam Player \n\uf0fc \nStrong Interpersonal Skills \n\uf0fc \nAdaptable \n\uf0fc \nHonesty \n\uf0fc \nMotivator \n \nHOBBIES \n \n\uf0fc \nDriving & riding (Bikes) \n\uf0fc \nPlaying Outdoor Sports (Cricket) \n\uf0fc \nWatching Movies \n \nCleared Compulsory Papers (IC-01) of Licentiate from Insurance Institute of India \n",
    "personal_info": {
        "name": "YESH SHIVHARE",
        "email": "yashshivhare353@gmail.com",
        "phone": "8823099701",
        "linkedin": "linkedin.com/in/yesh-shivhare-896975226",
        "github": null,
        "location": "Indore"
    },
    "resume_score": 90,
    "education_summary": "Post Graduate: Yes, Graduate (Bachelor's): Yes, UG (Diploma/ITI): No, HSC: Yes, SSC: Yes",
    "improvement_suggestions": [
        "List certifications or training programs.",
        "Include work experience or volunteering."
    ],
    "ai_skill_suggestions": [],
    "predicted_job_field": {
        "top_matches": [],
        "job_title": "No such job field found on server.",
        "skills": [
            "research",
            "data analysis",
            "excel",
            "market research",
            "nutrition"
        ],
        "preferred_location": "Indore",
        "recommended_courses": {}
    }
}