{
    "raw_text": "Jagruti Pandey \n\ud83d\udcde +91-9167660802 | \ud83d\udce7 jagudp18@gmail.com | \ud83d\udce7 Mumbai, Maharashtra \n\ud83d\udcbc Skilled in IOT, AI, ML, SQL, PLSQL, Power BI, Python, Excel \n\ud83d\udce7 GitHub: https://github.com/Jagruti-Pandey \n\ud83d\udce7 LinkedIn: https://www.linkedin.com/in/jagruti-pandey-769a6626b \nProfessional Summary \nDetail-oriented and motivated data analyst skilled in Power BI, Excel, Python, and SQL. \nExperienced in building interactive dashboards and AI-driven applications. Passionate \nabout transforming raw data into actionable insights. Eager to contribute analytical \nexpertise in a dynamic organization. \nEducation \nB.Sc. in Information Technology \nShree Shankar Narayan Education Trust\u2019s College, Thane \n2022 \u2013 2025 | Score: 76% \nClass XII \u2013 Maharashtra State Board \n2022 | Score: 67% | \ud83d\udcde 1st Position in Quiz Competition \nClass X \u2013 Maharashtra State Board \n2020 | Score: 72% \nCertifications \n\uf0b7 \nMaster Data Analyst Boot Camp- Ongoing (May 2025-Present) \n\uf0b7 Data Analyst with Python \u2013 Ongoing (May 2025 \u2013 Present) \n\uf0b7 Diploma in Computer Software Programming \u2013 Completed (June 2022) \nInternship Experience \nData Intern \u2013 Deloitte \n\ud83d\udcde April 2025 \n\u2022 Completed data tasks using Tableau and Excel \n\u2022 Worked on data visualization and spreadsheet analysis \nProjects \nTableau Dashboard 2(Tableau)-June 2025 \nI create dashboard based on total transactions by city , age groups , payment method \nusing map visual , card visual \nTableau Dashboard (Tableau)-June 2025 \nI create a dashboard based on profit, sales, and order quantity by month using Tableau \nand tools like bar chart, line chart, and pie chart \nProduction Dashboard (Excel)-June 2025 \nI create a Production Dashboard using Excel about region, gender, age groups with the \nhelp of 3D column, 3D bar, 3D line, 3D pie \nExcel Report Dashboard (Excel)-June 2025 \nI am creating an Excel report dashboard using a pie chart, column chart, bar chart, and \nline chart about total profit, expenses, and revenue \nUPI Transactions Data Analysis (Power BI)-June 2025 \nI create UPI transactions data analysis using line chart, column chart, slicer, matrix, \nnavigator, bookmarks, selection, filter \nInsurance Data Analysis (Power BI)-June 2025 \nIt is based on insurance using a donut chart, matrix, line chart, card, ribbon chart, and \nmulti-row card \nSales Dashboard (Power BI) \u2013 June 2025 \nCreated a comprehensive sales dashboard using stacked bar chart, map, line chart, \nslicers, and more \nMonthly Budget Tracker (Excel) \u2013 May 2025 \nDesigned a personal budget system with bar chart, pie chart, and table summaries \nE-commerce Sales Dashboard (Power BI) \u2013 April 2025 \nVisualized key sales metrics and trends for an online business using Power BI visuals \nAI Virtual Mouse (Python) \u2013 Jan 2025 \u2013 Apr 2025 \nDeveloped gesture recognition, voice command, and eye-tracking system using Python, \nMedia Pipe, and OpenCV \nSkills \nTechnical Tools: IOT, AI, ML, Python, SQL, Power BI, Excel (Advanced), Tableau, MS \nOffice, Java, JavaScript, HTML/CSS, PL/SQL, C, C++ \nLanguages: English, Hindi, Marathi (Fluent in Reading, Writing, Speaking) \nAchievements \n\u2022 TOEFL Score: 90 \n",
    "personal_info": {
        "name": "Jagruti Pandey",
        "email": "jagudp18@gmail.com",
        "phone": "9167660802",
        "linkedin": "linkedin.com/in/jagruti-pandey-769a6626b",
        "github": "https://github.com/Jagruti-Pandey",
        "location": "Mumbai"
    },
    "resume_score": 90,
    "education_summary": "Post Graduate: Yes, Graduate (Bachelor's): No, UG (Diploma/ITI): Yes, HSC: Yes, SSC: Yes",
    "improvement_suggestions": [
        "Add your Bachelor's degree qualification."
    ],
    "ai_skill_suggestions": [
        "business strategy",
        "modeling"
    ],
    "predicted_job_field": {
        "job_title": "Business Analyst",
        "skills": [
            "power bi",
            "tableau",
            "data visualization",
            "html",
            "css",
            "javascript",
            "sql",
            "excel",
            "tools",
            "mba",
            "python",
            "java"
        ],
        "preferred_location": "Mumbai",
        "recommended_courses": [
            "Business Analysis Fundamentals - https://www.udemy.com/course/business-analysis-fundamentals",
            "Business Analytics Specialization - https://www.coursera.org/specializations/business-analytics",
            "Excel for Business Analysts - https://www.linkedin.com/learning/excel-data-analysis"
        ]
    }
}