{
    "raw_text": "Pratik Bharne\nbharnepratik10@gmail.com\n \n9860332648\n \nghatkopar\n \nlinkedin.com/in/pratikbharne2002  \n \nProfile\nA highly motivated and detail-oriented Data and Business Analyst with expertise in data analysis, machine \nlearning, and process optimization. Skilled in tools like Excel, SQL, Python, Tableau, and Scikit learn to deliver \nactionable insights and support data-driven decisions. Experienced in leveraging ML models for predictive \nanalytics and automating workflows to enhance operational efficiency. Adept at collaborating with teams to \ngather requirements, design solutions, and drive strategic business improvements. Passionate about solving \ncomplex problems through advanced analytics and innovation.\nEducation\nB.E in Computer Science Engineering(AI&ML), \nG.V Acharya Institute of Engineering and Technology under Mumbai University\n08/2022 – 06/2025\nShelu - Raigad, India\nDiploma In Electrical Engineering, \nInstitute of Technology And Engineering Malegaon (Bk)\n08/2018 – 06/2022\nMalegaon(bk), India\nSSC 10th, SIES APJ MEMORIAL HIGH SCHOOL\n03/2018\nGhatkopar, India\nSkills\nAI&ML Programming Languages\n•Machine Learning • Programming: Python (NumPy, \nPandas, Scikit learn, TensorFlow, PyTorch)\n•ML Algorithms: Regression, Decision Trees, \nRandom Forests, SVM, K-Means, Gradient Boosting \n(XGBoost) \n•Data Preprocessing: Feature engineering, handling \nmissing data\n•Model Deployment: Flask, Streamlit \n•Visualization: pandas,Matplotlib, Seaborn, Plotly\nProgramming Language\n• Python\n• c language\nData Visualization Tools\n• Advanced Excel \n• Power BI \n• Tableau\nDatabase Management\n• Mysql\nCertificates\nMaster in Data Science & \nAnalytics with Artificial  \nIntelligence\n• Advanced Excel \n• Mysql \n• Power BI \n• Tablea \n• Machine Learning \n• Artificial Intelligence\nProjects\nBank Loan Report, based on Advance Excel\nDeveloped a comprehensive Bank Loan Report Dashboard to analyze key financial metrics, including total loan \napplications, funded amounts, and loan repayment statuses. The dashboard provided a clear breakdown of \ngood (86.18%) and bad loans (13.82%), along with insights on interest rates and debt-to-income ratios. \nInteractive filters allowed dynamic analysis based on loan grades and purposes. This project demonstrated \nskills in data visualization, financial analysis, and the use of tools like Excel/Tableau/Power BI to deliver \nactionable insights.\nHeart Failure clinical Prediction(ML)\nHeart Failure clinical Prediction(ML) Objective: Analyzed and predicted patient outcomes using clinical records \nto assist in early detection and treatment of heart failure. Methodology: Conducted data preprocessing, feature \nselection, and exploratory data analysis using Python libraries like Pandas, NumPy, Seaborn, and Matplotlib. \nBuilt predictive models leveraging classification algorithms. Results: Identified key features such as age, \nejection fraction, and serum creatinine that significantly impact patient outcomes. Achieved high accuracy in \npredictions, enhancing decision-making in healthcare\nVrinda Store Analysis(Power BI)\nVrinda Store Analysis(Power BI) Designed and developed a comprehensive Customer Analysis Dashboard to \nanalyze key demographic and purchasing trends for a customer base of 28.44K. Key findings included the most \nordered sizes (XXI), popular categories (Western Dress), and average customer age. The dashboard featured \ndynamic slicers for detailed filtering by category and date range, visualizing sales metrics by size, shipping \nstate, sales channel, and breakdowns by gender and age. Delivered actionable insights to help stakeholders \nrefine marketing strategies and enhance product offerings based on customer preferences and regional \nperformance\n",
    "personal_info": {
        "name": "Pratik Bharne",
        "email": "bharnepratik10@gmail.com",
        "phone": "9860332648",
        "linkedin": "linkedin.com/in/pratikbharne2002",
        "github": null,
        "location": "Mumbai"
    },
    "resume_score": 85,
    "education_summary": "Post Graduate: No, Doctorate: No, Graduate (Bachelor's): Yes, UG (Diploma/ITI): Yes, HSC: No, SSC: Yes",
    "improvement_suggestions": [
        "Consider adding or pursuing Postgraduate (Master's, PGD) or Doctorate education.",
        "Mention any internships or trainee roles you've done."
    ],
    "ai_skill_suggestions": [
        "seaborn",
        "data visualization",
        "clustering",
        "pytorch",
        "regression",
        "classification",
        "statistics",
        "scikit-learn",
        "flask",
        "matplotlib",
        "streamlit",
        "numpy",
        "machine learning",
        "tensorflow",
        "deep learning",
        "python"
    ],
    "predicted_job_field": {
        "top_matches": [
            {
                "title": "Data Scientist",
                "confidence": 0.85,
                "confidence_percent": "85%"
            },
            {
                "title": "AI/ML Engineer",
                "confidence": 0.68,
                "confidence_percent": "68%"
            },
            {
                "title": "AI Engineer",
                "confidence": 0.67,
                "confidence_percent": "67%"
            }
        ],
        "job_title": "Data Scientist",
        "skills": [
            "Advanced Excel",
            "Analytics with Artificial",
            "Artificial Intelligence",
            "Certificates",
            "Data Visualization Tools",
            "Database Management",
            "Decision Trees",
            "Feature engineering",
            "Flask",
            "Gradient Boosting",
            "Intelligence",
            "Machine Learning",
            "Matplotlib",
            "Mysql",
            "Pandas",
            "Plotly",
            "Power BI",
            "Programming Language",
            "PyTorch",
            "Python",
            "Python NumPy",
            "Random Forests",
            "Regression",
            "Scikit learn",
            "Seaborn",
            "Streamlit",
            "Tablea",
            "Tableau",
            "TensorFlow",
            "XGBoost",
            "c language",
            "handling",
            "missing data",
            "pandas"
        ],
        "preferred_location": "Mumbai",
        "recommended_courses": {
            "Data Scientist": [
                "Machine Learning by Andrew Ng - https://www.coursera.org/learn/machine-learning",
                "R Programming for Data Analysis - https://www.datacamp.com/courses/free-introduction-to-r",
                "Data Science with Python - https://www.coursera.org/specializations/data-science-python"
            ],
            "AI/ML Engineer": [
                "Deep Learning Specialization - https://www.coursera.org/specializations/deep-learning"
            ],
            "AI Engineer": [
                "Deep Learning Specialization - https://www.coursera.org/specializations/deep-learning",
                "Machine Learning by Andrew Ng - https://www.coursera.org/learn/machine-learning",
                "AI For Everyone - https://www.coursera.org/learn/ai-for-everyone"
            ]
        }
    }
}